MANIFEST.in
README.txt
setup.py
collective/__init__.py
collective.js.uilayout.egg-info/PKG-INFO
collective.js.uilayout.egg-info/SOURCES.txt
collective.js.uilayout.egg-info/dependency_links.txt
collective.js.uilayout.egg-info/namespace_packages.txt
collective.js.uilayout.egg-info/not-zip-safe
collective.js.uilayout.egg-info/requires.txt
collective.js.uilayout.egg-info/top_level.txt
collective/js/__init__.py
collective/js/uilayout/__init__.py
collective/js/uilayout/configure.zcml
collective/js/uilayout/jquery.layout-1.2.0.js
collective/js/uilayout/jquery.layout-1.2.0.min.js
collective/js/uilayout/jquery.layout.css
collective/js/uilayout/jquery.layout.plonekss.css
collective/js/uilayout/profiles/default/cssregistry.xml
collective/js/uilayout/profiles/default/jsregistry.xml
collective/js/uilayout/profiles/default/metadata.xml
collective/js/uilayout/tests/__init__.py
collective/js/uilayout/tests/base.py
collective/js/uilayout/tests/test_setup.py
docs/HISTORY.txt