Metadata-Version: 1.0
Name: collective.js.uilayout
Version: 1.2.0.3
Summary: UI.Layout JQuery plugin integration in portal_javascript
Home-page: http://plone.org/products/collective.js.uilayout
Author: Gerhard Weis
Author-email: gweis@gmx.at
License: GPL
Keywords: Plone,jQuery
Platform: UNKNOWN
Classifier: License :: OSI Approved :: GNU General Public License (GPL)
Classifier: Development Status :: 5 - Production/Stable
Classifier: Operating System :: OS Independent
Classifier: Programming Language :: Python
Classifier: Topic :: Software Development :: Libraries :: Python Modules
Classifier: Framework :: Plone
